mkdoclingo-1.4.0.dist-info/licenses/LICENSE
mkdocstrings_handlers/asp/__init__.py
mkdocstrings_handlers/asp/py.typed
mkdocstrings_handlers/asp/_internal/__init__.py
mkdocstrings_handlers/asp/_internal/config.py
mkdocstrings_handlers/asp/_internal/domain.py
mkdocstrings_handlers/asp/_internal/error.py
mkdocstrings_handlers/asp/_internal/handler.py
mkdocstrings_handlers/asp/_internal/collect/__init__.py
mkdocstrings_handlers/asp/_internal/collect/debug.py
mkdocstrings_handlers/asp/_internal/collect/extractors.py
mkdocstrings_handlers/asp/_internal/collect/load.py
mkdocstrings_handlers/asp/_internal/collect/syntax.py
mkdocstrings_handlers/asp/_internal/collect/queries/body.scm
mkdocstrings_handlers/asp/_internal/collect/queries/documentation_argument.scm
mkdocstrings_handlers/asp/_internal/collect/queries/documentation_predicate.scm
mkdocstrings_handlers/asp/_internal/collect/queries/head.scm
mkdocstrings_handlers/asp/_internal/collect/queries/predicate.scm
mkdocstrings_handlers/asp/_internal/collect/queries/show.scm
mkdocstrings_handlers/asp/_internal/render/__init__.py
mkdocstrings_handlers/asp/_internal/render/dependency_graph_context.py
mkdocstrings_handlers/asp/_internal/render/encodings_context.py
mkdocstrings_handlers/asp/_internal/render/glossary_context.py
mkdocstrings_handlers/asp/_internal/render/predicate_info.py
mkdocstrings_handlers/asp/_internal/render/predicate_table_context.py
mkdocstrings_handlers/asp/_internal/render/render_context.py
mkdocstrings_handlers/asp/templates/material/dependency_graph.html.jinja
mkdocstrings_handlers/asp/templates/material/documentation.html.jinja
mkdocstrings_handlers/asp/templates/material/encodings.html.jinja
mkdocstrings_handlers/asp/templates/material/glossary.html.jinja
mkdocstrings_handlers/asp/templates/material/glossary_references.html.jinja
mkdocstrings_handlers/asp/templates/material/icons.html.jinja
mkdocstrings_handlers/asp/templates/material/predicate_table.html.jinja
mkdocstrings_handlers/asp/templates/material/separator.html.jinja
mkdoclingo-1.4.0.dist-info/METADATA
mkdoclingo-1.4.0.dist-info/WHEEL
mkdoclingo-1.4.0.dist-info/entry_points.txt
mkdoclingo-1.4.0.dist-info/top_level.txt
mkdoclingo-1.4.0.dist-info/RECORD
