Metadata-Version: 2.4
Name: mkdoclingo
Version: 1.4.0
Summary: Mkdocs plugin to generate documentation from clingo files
Author-email: Potassco <hahnmartinlu@uni-potsdam.de>
License: MIT License
Project-URL: Homepage, https://github.com/potassco/mkdoclingo.git/
Requires-Python: >=3.11
License-File: LICENSE
Requires-Dist: clingo
Requires-Dist: mkdocstrings>=1.0.0
Requires-Dist: tree-sitter
Requires-Dist: tree-sitter-clingo>=1.0.3
Requires-Dist: pydantic
Requires-Dist: pygments_clingo
Requires-Dist: mkdocs>=1.5
Requires-Dist: mkdocs-material>=9.5
Requires-Dist: mkdocs-autorefs>=1.4
Provides-Extra: format
Requires-Dist: black; extra == "format"
Requires-Dist: isort; extra == "format"
Requires-Dist: autoflake; extra == "format"
Provides-Extra: lint-pylint
Requires-Dist: pylint; extra == "lint-pylint"
Requires-Dist: djlint; extra == "lint-pylint"
Provides-Extra: typecheck
Requires-Dist: types-setuptools; extra == "typecheck"
Requires-Dist: mypy; extra == "typecheck"
Requires-Dist: types-Markdown; extra == "typecheck"
Provides-Extra: test
Requires-Dist: coverage[toml]; extra == "test"
Requires-Dist: pytest; extra == "test"
Provides-Extra: doc
Requires-Dist: mkdocstrings[python]; extra == "doc"
Requires-Dist: mkdocs-literate-nav; extra == "doc"
Provides-Extra: dev
Requires-Dist: mkdoclingo[doc,lint_pylint,test,typecheck]; extra == "dev"
Dynamic: license-file
